wbaccounting/__init__.py
wbaccounting/apps.py
wbaccounting/dynamic_preferences_registry.py
wbaccounting/permissions.py
wbaccounting/urls.py
wbaccounting/admin/__init__.py
wbaccounting/admin/booking_entry.py
wbaccounting/admin/entry_accounting_information.py
wbaccounting/admin/invoice.py
wbaccounting/admin/invoice_type.py
wbaccounting/admin/transactions.py
wbaccounting/factories/__init__.py
wbaccounting/factories/booking_entry.py
wbaccounting/factories/entry_accounting_information.py
wbaccounting/factories/invoice.py
wbaccounting/factories/transactions.py
wbaccounting/files/__init__.py
wbaccounting/files/invoice_document_file.py
wbaccounting/files/utils.py
wbaccounting/generators/__init__.py
wbaccounting/generators/base.py
wbaccounting/io/handlers/__init__.py
wbaccounting/io/handlers/transactions.py
wbaccounting/io/parsers/__init__.py
wbaccounting/io/parsers/societe_generale_lux.py
wbaccounting/io/parsers/societe_generale_lux_prenotification.py
wbaccounting/migrations/0001_initial_squashed_squashed_0005_alter_bookingentry_counterparty_and_more.py
wbaccounting/migrations/0006_alter_invoice_status.py
wbaccounting/migrations/0007_alter_invoice_options.py
wbaccounting/migrations/0008_alter_invoice_options.py
wbaccounting/migrations/0009_invoicetype_alter_bookingentry_options_and_more.py
wbaccounting/migrations/0010_alter_bookingentry_options.py
wbaccounting/migrations/0011_transaction.py
wbaccounting/migrations/0012_entryaccountinginformation_external_invoice_users.py
wbaccounting/migrations/__init__.py
wbaccounting/models/__init__.py
wbaccounting/models/booking_entry.py
wbaccounting/models/entry_accounting_information.py
wbaccounting/models/invoice.py
wbaccounting/models/invoice_type.py
wbaccounting/models/model_tasks.py
wbaccounting/models/transactions.py
wbaccounting/processors/__init__.py
wbaccounting/processors/dummy_processor.py
wbaccounting/serializers/__init__.py
wbaccounting/serializers/booking_entry.py
wbaccounting/serializers/consolidated_invoice.py
wbaccounting-2.2.6.dist-info/METADATA
wbaccounting-2.2.6.dist-info/WHEEL
wbaccounting-2.2.6.dist-info/RECORD
