Metadata-Version: 2.4
Name: wbaccounting
Version: 2.2.6
Summary: A workbench module for managing invoicing and simple accounting.
Author-email: Christopher Wittlinger <c.wittlinger@stainly.com>
Requires-Dist: reportlab==3.*
Requires-Dist: schwifty==2024.5.*
Requires-Dist: wbcore
